mockingbird/__init__.py
mockingbird/main.py
mockingbird/blueprint/__init__.py
mockingbird/blueprint/engine.py
mockingbird/cli/__init__.py
mockingbird/common/exceptions.py
mockingbird/config/__init__.py
mockingbird/config/settings.py
mockingbird/generation/__init__.py
mockingbird/generation/core.py
mockingbird/generation/dependency_resolver.py
mockingbird/generation/execution_context.py
mockingbird/generation/generators.py
mockingbird/output/__init__.py
mockingbird/output/formatters.py
mockingbird/output/service.py
mockingbird/providers/commerce_provider.py
mockingbird_cli-0.6.0.dist-info/licenses/LICENSE
mockingbird_cli-0.6.0.dist-info/METADATA
mockingbird_cli-0.6.0.dist-info/WHEEL
mockingbird_cli-0.6.0.dist-info/entry_points.txt
mockingbird_cli-0.6.0.dist-info/top_level.txt
mockingbird_cli-0.6.0.dist-info/RECORD
