Metadata-Version: 2.4
Name: mockingbird-cli
Version: 0.6.0
Summary: A powerful CLI tool for generating realistic mock data with relationships and referential integrity
Author-email: Prasad Bhamidipati <prasadbhamidi@gmail.com>
Maintainer-email: Prasad Bhamidipati <prasadbhamidi@gmail.com>
License: MIT
Project-URL: Homepage, https://mockingbird.smallapps.in
Keywords: faker,mock-data,data-generator,cli,testing,fixtures,synthetic-data,relational-data,csv,json,parquet,relationships
Classifier: Development Status :: 4 - Beta
Classifier: Environment :: Console
Classifier: Intended Audience :: Developers
Classifier: Intended Audience :: Science/Research
Classifier: License :: OSI Approved :: MIT License
Classifier: Operating System :: OS Independent
Classifier: Programming Language :: Python :: 3
Classifier: Programming Language :: Python :: 3.11
Classifier: Programming Language :: Python :: 3.12
Classifier: Programming Language :: Python :: 3.13
Classifier: Programming Language :: Python :: Implementation :: CPython
Classifier: Programming Language :: Python :: Implementation :: PyPy
Classifier: Topic :: Software Development :: Libraries :: Python Modules
Classifier: Topic :: Software Development :: Testing
Classifier: Topic :: Software Development :: Testing :: Mocking
Classifier: Topic :: Utilities
Classifier: Typing :: Typed
Requires-Python: >=3.11
License-File: LICENSE
Requires-Dist: typer<1.0.0,>=0.16.0
Requires-Dist: duckdb<2.0.0,>=1.3.0
Requires-Dist: PyYAML<7.0.0,>=6.0.0
Requires-Dist: pyarrow>=15.0.0
Requires-Dist: python-dotenv<2.0.0,>=1.0.0
Requires-Dist: Faker>=20.0.0
Requires-Dist: asteval<2.0.0,>=1.0.0
Requires-Dist: rich>=13.0.0
Requires-Dist: pandas>=2.0.0
Requires-Dist: python-dateutil>=2.8.0
Provides-Extra: dev
Requires-Dist: pytest>=8.0.0; extra == "dev"
Requires-Dist: pytest-cov>=4.0.0; extra == "dev"
Requires-Dist: black>=23.0.0; extra == "dev"
Requires-Dist: isort>=5.12.0; extra == "dev"
Requires-Dist: mypy>=1.5.0; extra == "dev"
Requires-Dist: pre-commit>=3.0.0; extra == "dev"
Provides-Extra: docs
Requires-Dist: mkdocs>=1.5.0; extra == "docs"
Requires-Dist: mkdocs-material>=9.0.0; extra == "docs"
Dynamic: license-file
